Workbook

Sheet Raw
A1: Order ID | B1: Date | C1: Product | D1: Price | E1: Quantity | F1: Purchase Type | G1: Payment Method | H1: Manager | I1: City
A2: 10452 | B2: 44872 | C2: Fries | D2: 3.49 | E2: 573.0659 | F2: Online | G2: Gift Card | H2: Tom Jackson | I2: London
A3: 10453 | B3: 44872 | C3: Beverages | D3: 2.95 | E3: 745.76271 | F3: Online | G3: Gift Card | H3: Pablo Perez | I3: Madrid
A4: 10454 | B4: 44872 | C4: Sides & Other | D4: 4.99 | E4: 200.4008 | F4: In-store | G4: Gift Card | H4: Joao Silva | I4: Lisbon
A5: 10455 | B5: 44873 | C5: Burgers | D5: 12.99 | E5: 569.66898 | F5: In-store | G5: Credit Card | H5: Walter Muller | I5: Berlin
A6: 10456 | B6: 44873 | C6: Chicken Sandwiches | D6: 9.95 | E6: 201.00503 | F6: In-store | G6: Credit Card | H6: Walter Muller | I6: Berlin
A7: 10457 | B7: 44873 | C7: Fries | D7: 3.49 | E7: 573.0659 | F7: In-store | G7: Credit Card | H7: Remy Monet | I7: Paris
A8: 10457 | B8: 44873 | C8: Fries | D8: 3.49 | E8: 573.0659 | F8: In-store | G8: Credit Card | H8: Remy Monet | I8: Paris
A9: 10459 | B9: 44873 | C9: Sides & Other | D9: 4.99 | E9: 200.4008 | F9: In-store | G9: Credit Card | H9: Walter Muller | I9: Berlin
A10: 10460 | B10: 44874 | C10: Burgers | D10: 12.99 | E10: 554.27252 | F10: In-store | G10: Credit Card | H10: Remy Monet | I10: Paris
A11: 10461 | B11: 44874 | C11: Chicken Sandwiches | D11: 9.95 | E11: 201.00503 | F11: In-store | G11: Credit Card | H11: Remy Monet | I11: Paris
A12: 10462 | B12: 44874 | C12: Fries | D12: 3.49 | E12: 573.0659 | F12: In-store | G12: Credit Card | H12: Remy Monet | I12: Paris
A13: 10463 | B13: 44874 | C13: Beverages | D13: 2.95 | E13: 677.9661 | F13: In-store | G13: Credit Card | H13: Remy Monet | I13: Paris
... A263: 10713 | B263: 44924 | C263: Beverages | D263: 2.95 | E263: 677.9661 | F263: Drive-thru | G263: Gift Card | H263: Walter Muller | I263: Berlin

Sheet PRACTICE
A1: StudentID | B1: Name | C1: Age | D1: Gender | E1: Department | F1: Marks | G1: City | H1: Marks*3 | I1: Marks*3
A2: 101 | B2: Ananya | C2: 21 | D2: Female | E2: CSE | F2: 85 | G2: Chennai | H2: =F2*3 -> 255 | I2: 255
A3: 102 | B3: Rahul | C3: 22 | D3: Male | E3: ECE | F3: 78 | G3: Bangalore | H3: =F3*3 -> 234 | I3: 234
A4: 103 | B4: Meena | C4: 20 | D4: Female | E4: IT | F4: 92 | G4: Hyderabad | H4: =F4*3 -> 276 | I4: 276
A5: 104 | B5: Arjun | C5: 23 | D5: Male | E5: EEE | F5: 67 | G5: Mumbai | H5: =F5*3 -> 201 | I5: 201
A6: 105 | B6: Priya | C6: 21 | D6: Female | E6: CSE | F6: 88 | G6: Chennai | H6: =F6*3 -> 264 | I6: 264
A7: 106 | B7: Karan | C7: 22 | D7: Male | E7: IT | F7: 74 | G7: Delhi | H7: =F7*3 -> 222 | I7: 222
A8: 107 | B8: Sneha | C8: 20 | D8: Female | E8: ECE | F8: 81 | G8: Pune | H8: =F8*3 -> 243 | I8: 243
A9: 108 | B9: Vikram | C9: 24 | D9: Male | E9: EEE | F9: 69 | G9: Kolkata | H9: =F9*3 -> 207 | I9: 207
A10: 109 | B10: Divya | C10: 21 | D10: Female | E10: CSE | F10: 95 | G10: Chennai | H10: =F10*3 -> 285 | I10: 285
A11: 110 | B11: Rohit | C11: 23 | D11: Male | E11: IT | F11: 72 | G11: Bangalore | H11: =F11*3 -> 216 | I11: 216

Sheet EXCEL Shortcuts
A1: S.No | B1: Short cut | C1: Usage
A2: 1 | B2: Ctrl+Home | C2: Go to the first entry
A3: 2 | B3: Ctrl+End | C3: Go to last entry
A4: 3 | B4: Ctrl+Shift+down arrow | C4: Select/unselect the entire row from first to last entry
A5: 4 | B5: Ctrl+Shift+up arrow | C5: Select/unselect the entire row from last to first entry
A6: 5 | B6: Right clicek->paste values | C6: This will just paste the values of the column on which some formula is applied(dependent on i/p column)
A7: 6
A8: 7
A9: 8
A10: 9
A11: 10
A12: 11
A13: 12
A14: 13
A15: 14
A16: 15
A17: 16
A18: 17
... A31: 30

Sheet Clean
B2: Order ID | C2: Date | D2: Product | E2: Price | F2: Quantity | G2: Cost | H2: City | I2: Country | J2: Purchase Type | K2: Payment Method | L2: Manager | M2: Revenue
B3: 10452 | C3: 44872 | D3: Fries | E3: 3.49 | F3: 574 | G3: 0.88 | H3: #VALUE! | I3: {=_FV(H3,"Country/region",TRUE)} -> #VALUE! | J3: Online | K3: Gift Card | L3: Tom Jackson | M3: =Table1[[#This Row],[Price]]*Table1[[#This Row],[Quantity]] -> 2003.26
B4: 10453 | C4: 44872 | D4: Beverages | E4: 2.95 | F4: 746 | G4: 0.47 | H4: #VALUE! | I4: {=_FV(H4,"Country/region",TRUE)} -> #VALUE! | J4: Online | K4: Gift Card | L4: Pablo Perez | M4: =Table1[[#This Row],[Price]]*Table1[[#This Row],[Quantity]] -> 2200.7
B5: 10454 | C5: 44872 | D5: Sides & Other | E5: 4.99 | F5: 201 | G5: 2.25 | H5: #VALUE! | I5: {=_FV(H5,"Country/region",TRUE)} -> #VALUE! | J5: In-store | K5: Gift Card | L5: Joao Silva | M5: =Table1[[#This Row],[Price]]*Table1[[#This Row],[Quantity]] -> 1002.99
B6: 10455 | C6: 44873 | D6: Burgers | E6: 12.99 | F6: 570 | G6: 4.32 | H6: #VALUE! | I6: {=_FV(H6,"Country/region",TRUE)} -> #VALUE! | J6: In-store | K6: Credit Card | L6: Walter Muller | M6: =Table1[[#This Row],[Price]]*Table1[[#This Row],[Quantity]] -> 7404.3
B7: 10456 | C7: 44873 | D7: Chicken Sandwiches | E7: 9.95 | F7: 202 | G7: 2.85 | H7: #VALUE! | I7: {=_FV(H7,"Country/region",TRUE)} -> #VALUE! | J7: In-store | K7: Credit Card | L7: Walter Muller | M7: =Table1[[#This Row],[Price]]*Table1[[#This Row],[Quantity]] -> 2009.9
B8: 10457 | C8: 44873 | D8: Fries | E8: 3.49 | F8: 574 | G8: 0.88 | H8: #VALUE! | I8: {=_FV(H8,"Country/region",TRUE)} -> #VALUE! | J8: In-store | K8: Credit Card | L8: Remy Monet | M8: =Table1[[#This Row],[Price]]*Table1[[#This Row],[Quantity]] -> 2003.26
B9: 10459 | C9: 44873 | D9: Sides & Other | E9: 4.99 | F9: 201 | G9: 2.25 | H9: #VALUE! | I9: {=_FV(H9,"Country/region",TRUE)} -> #VALUE! | J9: In-store | K9: Credit Card | L9: Remy Monet | M9: =Table1[[#This Row],[Price]]*Table1[[#This Row],[Quantity]] -> 1002.99
B10: 10460 | C10: 44874 | D10: Burgers | E10: 12.99 | F10: 555 | G10: 4.32 | H10: #VALUE! | I10: {=_FV(H10,"Country/region",TRUE)} -> #VALUE! | J10: In-store | K10: Credit Card | L10: Walter Muller | M10: =Table1[[#This Row],[Price]]*Table1[[#This Row],[Quantity]] -> 7209.45
B11: 10461 | C11: 44874 | D11: Chicken Sandwiches | E11: 9.95 | F11: 202 | G11: 2.85 | H11: #VALUE! | I11: {=_FV(H11,"Country/region",TRUE)} -> #VALUE! | J11: In-store | K11: Credit Card | L11: Remy Monet | M11: =Table1[[#This Row],[Price]]*Table1[[#This Row],[Quantity]] -> 2009.9
B12: 10462 | C12: 44874 | D12: Fries | E12: 3.49 | F12: 574 | G12: 0.88 | H12: #VALUE! | I12: {=_FV(H12,"Country/region",TRUE)} -> #VALUE! | J12: In-store | K12: Credit Card | L12: Remy Monet | M12: =Table1[[#This Row],[Price]]*Table1[[#This Row],[Quantity]] -> 2003.26
B13: 10463 | C13: 44874 | D13: Beverages | E13: 2.95 | F13: 678 | G13: 0.47 | H13: #VALUE! | I13: {=_FV(H13,"Country/region",TRUE)} -> #VALUE! | J13: In-store | K13: Credit Card | L13: Remy Monet | M13: =Table1[[#This Row],[Price]]*Table1[[#This Row],[Quantity]] -> 2000.1
B14: 10464 | C14: 44874 | D14: Sides & Other | E14: 4.99 | F14: 201 | G14: 2.25 | H14: #VALUE! | I14: {=_FV(H14,"Country/region",TRUE)} -> #VALUE! | J14: In-store | K14: Credit Card | L14: Remy Monet | M14: =Table1[[#This Row],[Price]]*Table1[[#This Row],[Quantity]] -> 1002.99
... B256: 10713 | C256: 44924 | D256: Beverages | E256: 2.95 | F256: 678 | G256: 0.47 | H256: #VALUE! | I256: {=_FV(H256,"Country/region",TRUE)} -> #VALUE! | J256: Drive-thru | K256: Gift Card | L256: Walter Muller | M256: =Table1[[#This Row],[Price]]*Table1[[#This Row],[Quantity]] -> 2000.1

Sheet Analysis
B2: Data Analysis Questions
B4: 1) What is our best selling product?
B6: 2) What is our total revenue?
B8: 3) What is the revenue breakdown by payment method?

Sheet Findings
B2: Select Manager -> | C2: Pablo Perez | J2: Tom Jackson
J3: Pablo Perez
B4: Geography | J4: Joao Silva
B5: Country | C5: =_xlfn.XLOOKUP(C2,Table1[Manager],Table1[Country]) -> #VALUE! | J5: Walter Muller
B6: City | C6: =_xlfn.XLOOKUP(C2,Table1[Manager],Table1[City]) -> #VALUE! | J6: Remy Monet
B8: Revenue
B9: Fries | C9: =SUMIFS(Table1[Revenue],Table1[Product],Findings!B9,Table1[Manager],Findings!$C$2) -> 17219.66
B10: Beverages | C10: =SUMIFS(Table1[Revenue],Table1[Product],Findings!B10,Table1[Manager],Findings!$C$2) -> 18402.1
B11: Sides & Other | C11: =SUMIFS(Table1[Revenue],Table1[Product],Findings!B11,Table1[Manager],Findings!$C$2) -> 9026.91
B12: Burgers | C12: =SUMIFS(Table1[Revenue],Table1[Product],Findings!B12,Table1[Manager],Findings!$C$2) -> 73692.27
B13: Chicken Sandwiches | C13: =SUMIFS(Table1[Revenue],Table1[Product],Findings!B13,Table1[Manager],Findings!$C$2) -> 18089.1
B14: Total | C14: =SUM(C9:C13) -> 136430.04
